// 
// Decompiled by Procyon v0.5.36
// 

public final class Game117
{
    public String Class1;
    public int Class2;
    public int Class3;
    public int Class4;
    public int Class5;
    public int Class6;
    public int Class7;
    public int Class8;
    public int Class9;
    public String Class10;
    public String Class11;
    public String Class12;
    public String Class13;
    public int Class14;
    public int Class15;
    public Item[] Class16;
    
    public Game117() {
        this.Class1 = "";
        this.Class10 = "";
        this.Class11 = "";
        this.Class12 = "";
        this.Class13 = "";
        new MyVector();
    }
    
    public final void Class1(final String p0) {
        // 
        // This method could not be decompiled.
        // 
        // Original Bytecode:
        // 
        //     1: ldc             "\n"
        //     3: invokestatic    Game20.Class1:(Ljava/lang/String;Ljava/lang/String;)[Ljava/lang/String;
        //     6: astore_1       
        //     7: aload_0        
        //     8: ldc             ""
        //    10: putfield        Game117.Class12:Ljava/lang/String;
        //    13: iconst_0       
        //    14: istore_2       
        //    15: goto            613
        //    18: aload_1        
        //    19: iload_2        
        //    20: aaload         
        //    21: invokevirtual   java/lang/String.trim:()Ljava/lang/String;
        //    24: dup            
        //    25: astore_3       
        //    26: ldc             ""
        //    28: invokevirtual   java/lang/String.equals:(Ljava/lang/Object;)Z
        //    31: ifne            610
        //    34: aload_3        
        //    35: ldc             ","
        //    37: invokestatic    Game20.Class1:(Ljava/lang/String;Ljava/lang/String;)[Ljava/lang/String;
        //    40: dup            
        //    41: astore_3       
        //    42: iconst_0       
        //    43: aaload         
        //    44: astore          4
        //    46: aload_3        
        //    47: iconst_1       
        //    48: aaload         
        //    49: invokestatic    java/lang/Integer.parseInt:(Ljava/lang/String;)I
        //    52: dup            
        //    53: istore          5
        //    55: ifne            136
        //    58: ldc             "c0"
        //    60: aload           4
        //    62: invokestatic    java/lang/String.valueOf:(Ljava/lang/Object;)Ljava/lang/String;
        //    65: invokevirtual   java/lang/String.concat:(Ljava/lang/String;)Ljava/lang/String;
        //    68: astore          4
        //    70: new             Ljava/lang/StringBuffer;
        //    73: dup            
        //    74: aload           4
        //    76: invokestatic    java/lang/String.valueOf:(Ljava/lang/Object;)Ljava/lang/String;
        //    79: invokespecial   java/lang/StringBuffer.<init>:(Ljava/lang/String;)V
        //    82: getstatic       Game86.Class348:[Ljava/lang/String;
        //    85: iconst_1       
        //    86: aaload         
        //    87: invokevirtual   java/lang/StringBuffer.append:(Ljava/lang/String;)Ljava/lang/StringBuffer;
        //    90: ldc             " "
        //    92: invokevirtual   java/lang/StringBuffer.append:(Ljava/lang/String;)Ljava/lang/StringBuffer;
        //    95: aload_3        
        //    96: iconst_2       
        //    97: aaload         
        //    98: invokestatic    Game20.Class1:(Ljava/lang/String;)Ljava/lang/String;
        //   101: invokevirtual   java/lang/StringBuffer.append:(Ljava/lang/String;)Ljava/lang/StringBuffer;
        //   104: ldc             " "
        //   106: invokevirtual   java/lang/StringBuffer.append:(Ljava/lang/String;)Ljava/lang/StringBuffer;
        //   109: getstatic       Game86.Class348:[Ljava/lang/String;
        //   112: iconst_0       
        //   113: aaload         
        //   114: invokevirtual   java/lang/StringBuffer.append:(Ljava/lang/String;)Ljava/lang/StringBuffer;
        //   117: ldc             " "
        //   119: invokevirtual   java/lang/StringBuffer.append:(Ljava/lang/String;)Ljava/lang/StringBuffer;
        //   122: aload_3        
        //   123: iconst_3       
        //   124: aaload         
        //   125: invokevirtual   java/lang/StringBuffer.append:(Ljava/lang/String;)Ljava/lang/StringBuffer;
        //   128: invokevirtual   java/lang/StringBuffer.toString:()Ljava/lang/String;
        //   131: astore          4
        //   133: goto            574
        //   136: iload           5
        //   138: iconst_1       
        //   139: if_icmpne       225
        //   142: ldc             "c1"
        //   144: aload           4
        //   146: invokestatic    java/lang/String.valueOf:(Ljava/lang/Object;)Ljava/lang/String;
        //   149: invokevirtual   java/lang/String.concat:(Ljava/lang/String;)Ljava/lang/String;
        //   152: astore          4
        //   154: new             Ljava/lang/StringBuffer;
        //   157: dup            
        //   158: aload           4
        //   160: invokestatic    java/lang/String.valueOf:(Ljava/lang/Object;)Ljava/lang/String;
        //   163: invokespecial   java/lang/StringBuffer.<init>:(Ljava/lang/String;)V
        //   166: ldc             " "
        //   168: invokevirtual   java/lang/StringBuffer.append:(Ljava/lang/String;)Ljava/lang/StringBuffer;
        //   171: getstatic       Game86.Class348:[Ljava/lang/String;
        //   174: iconst_2       
        //   175: aaload         
        //   176: invokevirtual   java/lang/StringBuffer.append:(Ljava/lang/String;)Ljava/lang/StringBuffer;
        //   179: ldc             " "
        //   181: invokevirtual   java/lang/StringBuffer.append:(Ljava/lang/String;)Ljava/lang/StringBuffer;
        //   184: aload_3        
        //   185: iconst_2       
        //   186: aaload         
        //   187: invokestatic    Game20.Class1:(Ljava/lang/String;)Ljava/lang/String;
        //   190: invokevirtual   java/lang/StringBuffer.append:(Ljava/lang/String;)Ljava/lang/StringBuffer;
        //   193: ldc             " "
        //   195: invokevirtual   java/lang/StringBuffer.append:(Ljava/lang/String;)Ljava/lang/StringBuffer;
        //   198: getstatic       Game86.Class348:[Ljava/lang/String;
        //   201: iconst_0       
        //   202: aaload         
        //   203: invokevirtual   java/lang/StringBuffer.append:(Ljava/lang/String;)Ljava/lang/StringBuffer;
        //   206: ldc             " "
        //   208: invokevirtual   java/lang/StringBuffer.append:(Ljava/lang/String;)Ljava/lang/StringBuffer;
        //   211: aload_3        
        //   212: iconst_3       
        //   213: aaload         
        //   214: invokevirtual   java/lang/StringBuffer.append:(Ljava/lang/String;)Ljava/lang/StringBuffer;
        //   217: invokevirtual   java/lang/StringBuffer.toString:()Ljava/lang/String;
        //   220: astore          4
        //   222: goto            574
        //   225: iload           5
        //   227: iconst_2       
        //   228: if_icmpne       314
        //   231: ldc             "c2"
        //   233: aload           4
        //   235: invokestatic    java/lang/String.valueOf:(Ljava/lang/Object;)Ljava/lang/String;
        //   238: invokevirtual   java/lang/String.concat:(Ljava/lang/String;)Ljava/lang/String;
        //   241: astore          4
        //   243: new             Ljava/lang/StringBuffer;
        //   246: dup            
        //   247: aload           4
        //   249: invokestatic    java/lang/String.valueOf:(Ljava/lang/Object;)Ljava/lang/String;
        //   252: invokespecial   java/lang/StringBuffer.<init>:(Ljava/lang/String;)V
        //   255: ldc             " "
        //   257: invokevirtual   java/lang/StringBuffer.append:(Ljava/lang/String;)Ljava/lang/StringBuffer;
        //   260: getstatic       Game86.Class348:[Ljava/lang/String;
        //   263: iconst_3       
        //   264: aaload         
        //   265: invokevirtual   java/lang/StringBuffer.append:(Ljava/lang/String;)Ljava/lang/StringBuffer;
        //   268: ldc             " "
        //   270: invokevirtual   java/lang/StringBuffer.append:(Ljava/lang/String;)Ljava/lang/StringBuffer;
        //   273: aload_3        
        //   274: iconst_2       
        //   275: aaload         
        //   276: invokestatic    Game20.Class1:(Ljava/lang/String;)Ljava/lang/String;
        //   279: invokevirtual   java/lang/StringBuffer.append:(Ljava/lang/String;)Ljava/lang/StringBuffer;
        //   282: ldc             " "
        //   284: invokevirtual   java/lang/StringBuffer.append:(Ljava/lang/String;)Ljava/lang/StringBuffer;
        //   287: getstatic       Game86.Class348:[Ljava/lang/String;
        //   290: iconst_0       
        //   291: aaload         
        //   292: invokevirtual   java/lang/StringBuffer.append:(Ljava/lang/String;)Ljava/lang/StringBuffer;
        //   295: ldc             " "
        //   297: invokevirtual   java/lang/StringBuffer.append:(Ljava/lang/String;)Ljava/lang/StringBuffer;
        //   300: aload_3        
        //   301: iconst_3       
        //   302: aaload         
        //   303: invokevirtual   java/lang/StringBuffer.append:(Ljava/lang/String;)Ljava/lang/StringBuffer;
        //   306: invokevirtual   java/lang/StringBuffer.toString:()Ljava/lang/String;
        //   309: astore          4
        //   311: goto            574
        //   314: iload           5
        //   316: iconst_3       
        //   317: if_icmpne       403
        //   320: ldc             "c1"
        //   322: aload           4
        //   324: invokestatic    java/lang/String.valueOf:(Ljava/lang/Object;)Ljava/lang/String;
        //   327: invokevirtual   java/lang/String.concat:(Ljava/lang/String;)Ljava/lang/String;
        //   330: astore          4
        //   332: new             Ljava/lang/StringBuffer;
        //   335: dup            
        //   336: aload           4
        //   338: invokestatic    java/lang/String.valueOf:(Ljava/lang/Object;)Ljava/lang/String;
        //   341: invokespecial   java/lang/StringBuffer.<init>:(Ljava/lang/String;)V
        //   344: ldc             " "
        //   346: invokevirtual   java/lang/StringBuffer.append:(Ljava/lang/String;)Ljava/lang/StringBuffer;
        //   349: getstatic       Game86.Class348:[Ljava/lang/String;
        //   352: iconst_4       
        //   353: aaload         
        //   354: invokevirtual   java/lang/StringBuffer.append:(Ljava/lang/String;)Ljava/lang/StringBuffer;
        //   357: ldc             " "
        //   359: invokevirtual   java/lang/StringBuffer.append:(Ljava/lang/String;)Ljava/lang/StringBuffer;
        //   362: aload_3        
        //   363: iconst_2       
        //   364: aaload         
        //   365: invokestatic    Game20.Class1:(Ljava/lang/String;)Ljava/lang/String;
        //   368: invokevirtual   java/lang/StringBuffer.append:(Ljava/lang/String;)Ljava/lang/StringBuffer;
        //   371: ldc             " "
        //   373: invokevirtual   java/lang/StringBuffer.append:(Ljava/lang/String;)Ljava/lang/StringBuffer;
        //   376: getstatic       Game86.Class348:[Ljava/lang/String;
        //   379: iconst_0       
        //   380: aaload         
        //   381: invokevirtual   java/lang/StringBuffer.append:(Ljava/lang/String;)Ljava/lang/StringBuffer;
        //   384: ldc             " "
        //   386: invokevirtual   java/lang/StringBuffer.append:(Ljava/lang/String;)Ljava/lang/StringBuffer;
        //   389: aload_3        
        //   390: iconst_3       
        //   391: aaload         
        //   392: invokevirtual   java/lang/StringBuffer.append:(Ljava/lang/String;)Ljava/lang/StringBuffer;
        //   395: invokevirtual   java/lang/StringBuffer.toString:()Ljava/lang/String;
        //   398: astore          4
        //   400: goto            574
        //   403: iload           5
        //   405: iconst_4       
        //   406: if_icmpne       487
        //   409: ldc             "c1"
        //   411: aload           4
        //   413: invokestatic    java/lang/String.valueOf:(Ljava/lang/Object;)Ljava/lang/String;
        //   416: invokevirtual   java/lang/String.concat:(Ljava/lang/String;)Ljava/lang/String;
        //   419: astore          4
        //   421: new             Ljava/lang/StringBuffer;
        //   424: dup            
        //   425: aload           4
        //   427: invokestatic    java/lang/String.valueOf:(Ljava/lang/Object;)Ljava/lang/String;
        //   430: invokespecial   java/lang/StringBuffer.<init>:(Ljava/lang/String;)V
        //   433: getstatic       Game86.Class348:[Ljava/lang/String;
        //   436: iconst_5       
        //   437: aaload         
        //   438: invokevirtual   java/lang/StringBuffer.append:(Ljava/lang/String;)Ljava/lang/StringBuffer;
        //   441: ldc             " "
        //   443: invokevirtual   java/lang/StringBuffer.append:(Ljava/lang/String;)Ljava/lang/StringBuffer;
        //   446: aload_3        
        //   447: iconst_2       
        //   448: aaload         
        //   449: invokestatic    Game20.Class1:(Ljava/lang/String;)Ljava/lang/String;
        //   452: invokevirtual   java/lang/StringBuffer.append:(Ljava/lang/String;)Ljava/lang/StringBuffer;
        //   455: ldc             " "
        //   457: invokevirtual   java/lang/StringBuffer.append:(Ljava/lang/String;)Ljava/lang/StringBuffer;
        //   460: getstatic       Game86.Class348:[Ljava/lang/String;
        //   463: iconst_0       
        //   464: aaload         
        //   465: invokevirtual   java/lang/StringBuffer.append:(Ljava/lang/String;)Ljava/lang/StringBuffer;
        //   468: ldc             " "
        //   470: invokevirtual   java/lang/StringBuffer.append:(Ljava/lang/String;)Ljava/lang/StringBuffer;
        //   473: aload_3        
        //   474: iconst_3       
        //   475: aaload         
        //   476: invokevirtual   java/lang/StringBuffer.append:(Ljava/lang/String;)Ljava/lang/StringBuffer;
        //   479: invokevirtual   java/lang/StringBuffer.toString:()Ljava/lang/String;
        //   482: astore          4
        //   484: goto            574
        //   487: iload           5
        //   489: iconst_5       
        //   490: if_icmpne       574
        //   493: ldc             "c2"
        //   495: aload           4
        //   497: invokestatic    java/lang/String.valueOf:(Ljava/lang/Object;)Ljava/lang/String;
        //   500: invokevirtual   java/lang/String.concat:(Ljava/lang/String;)Ljava/lang/String;
        //   503: astore          4
        //   505: new             Ljava/lang/StringBuffer;
        //   508: dup            
        //   509: aload           4
        //   511: invokestatic    java/lang/String.valueOf:(Ljava/lang/Object;)Ljava/lang/String;
        //   514: invokespecial   java/lang/StringBuffer.<init>:(Ljava/lang/String;)V
        //   517: ldc             " "
        //   519: invokevirtual   java/lang/StringBuffer.append:(Ljava/lang/String;)Ljava/lang/StringBuffer;
        //   522: getstatic       Game86.Class348:[Ljava/lang/String;
        //   525: bipush          6
        //   527: aaload         
        //   528: invokevirtual   java/lang/StringBuffer.append:(Ljava/lang/String;)Ljava/lang/StringBuffer;
        //   531: ldc             " "
        //   533: invokevirtual   java/lang/StringBuffer.append:(Ljava/lang/String;)Ljava/lang/StringBuffer;
        //   536: aload_3        
        //   537: iconst_2       
        //   538: aaload         
        //   539: invokestatic    Game20.Class1:(Ljava/lang/String;)Ljava/lang/String;
        //   542: invokevirtual   java/lang/StringBuffer.append:(Ljava/lang/String;)Ljava/lang/StringBuffer;
        //   545: ldc             " "
        //   547: invokevirtual   java/lang/StringBuffer.append:(Ljava/lang/String;)Ljava/lang/StringBuffer;
        //   550: getstatic       Game86.Class348:[Ljava/lang/String;
        //   553: iconst_0       
        //   554: aaload         
        //   555: invokevirtual   java/lang/StringBuffer.append:(Ljava/lang/String;)Ljava/lang/StringBuffer;
        //   558: ldc             " "
        //   560: invokevirtual   java/lang/StringBuffer.append:(Ljava/lang/String;)Ljava/lang/StringBuffer;
        //   563: aload_3        
        //   564: iconst_3       
        //   565: aaload         
        //   566: invokevirtual   java/lang/StringBuffer.append:(Ljava/lang/String;)Ljava/lang/StringBuffer;
        //   569: invokevirtual   java/lang/StringBuffer.toString:()Ljava/lang/String;
        //   572: astore          4
        //   574: aload_0        
        //   575: dup            
        //   576: getfield        Game117.Class12:Ljava/lang/String;
        //   579: new             Ljava/lang/StringBuffer;
        //   582: dup_x1         
        //   583: swap           
        //   584: invokestatic    java/lang/String.valueOf:(Ljava/lang/Object;)Ljava/lang/String;
        //   587: invokespecial   java/lang/StringBuffer.<init>:(Ljava/lang/String;)V
        //   590: aload           4
        //   592: invokevirtual   java/lang/StringBuffer.append:(Ljava/lang/String;)Ljava/lang/StringBuffer;
        //   595: ldc             "\n"
        //   597: invokevirtual   java/lang/StringBuffer.append:(Ljava/lang/String;)Ljava/lang/StringBuffer;
        //   600: invokevirtual   java/lang/StringBuffer.toString:()Ljava/lang/String;
        //   603: putfield        Game117.Class12:Ljava/lang/String;
        //   606: goto            610
        //   609: pop            
        //   610: iinc            2, 1
        //   613: iload_2        
        //   614: aload_1        
        //   615: arraylength    
        //   616: if_icmplt       18
        //   619: return         
        //   620: pop            
        //   621: return         
        //    StackMap: 00 0B 00 12 00 03 07 00 02 07 00 36 01 00 00 00 88 00 06 07 00 02 07 00 36 01 07 00 36 07 00 38 01 00 00 00 E1 00 06 07 00 02 07 00 36 01 07 00 36 07 00 38 01 00 00 01 3A 00 06 07 00 02 07 00 36 01 07 00 36 07 00 38 01 00 00 01 93 00 06 07 00 02 07 00 36 01 07 00 36 07 00 38 01 00 00 01 E7 00 06 07 00 02 07 00 36 01 07 00 36 07 00 38 01 00 00 02 3E 00 06 07 00 02 07 00 36 01 07 00 36 07 00 38 01 00 00 02 61 00 04 07 00 02 07 00 36 01 07 00 04 00 01 07 00 2D 02 62 00 04 07 00 02 07 00 36 01 07 00 04 00 00 02 65 00 03 07 00 02 07 00 36 01 00 00 02 6C 00 02 07 00 02 07 00 36 00 01 07 00 2D
        //    Exceptions:
        //  Try           Handler
        //  Start  End    Start  End    Type                 
        //  -----  -----  -----  -----  ---------------------
        //  34     606    609    610    Ljava/lang/Exception;
        //  13     619    620    622    Ljava/lang/Exception;
        // 
        // The error that occurred was:
        // 
        // java.lang.NullPointerException
        //     at com.strobel.assembler.ir.StackMappingVisitor.push(StackMappingVisitor.java:290)
        //     at com.strobel.assembler.ir.StackMappingVisitor$InstructionAnalyzer.execute(StackMappingVisitor.java:833)
        //     at com.strobel.assembler.ir.StackMappingVisitor$InstructionAnalyzer.visit(StackMappingVisitor.java:398)
        //     at com.strobel.decompiler.ast.AstBuilder.performStackAnalysis(AstBuilder.java:2030)
        //     at com.strobel.decompiler.ast.AstBuilder.build(AstBuilder.java:108)
        //     at com.strobel.decompiler.languages.java.ast.AstMethodBodyBuilder.createMethodBody(AstMethodBodyBuilder.java:211)
        //     at com.strobel.decompiler.languages.java.ast.AstMethodBodyBuilder.createMethodBody(AstMethodBodyBuilder.java:99)
        //     at com.strobel.decompiler.languages.java.ast.AstBuilder.createMethodBody(AstBuilder.java:782)
        //     at com.strobel.decompiler.languages.java.ast.AstBuilder.createMethod(AstBuilder.java:675)
        //     at com.strobel.decompiler.languages.java.ast.AstBuilder.addTypeMembers(AstBuilder.java:552)
        //     at com.strobel.decompiler.languages.java.ast.AstBuilder.createTypeCore(AstBuilder.java:519)
        //     at com.strobel.decompiler.languages.java.ast.AstBuilder.createTypeNoCache(AstBuilder.java:161)
        //     at com.strobel.decompiler.languages.java.ast.AstBuilder.createType(AstBuilder.java:150)
        //     at com.strobel.decompiler.languages.java.ast.AstBuilder.addType(AstBuilder.java:125)
        //     at com.strobel.decompiler.languages.java.JavaLanguage.buildAst(JavaLanguage.java:71)
        //     at com.strobel.decompiler.languages.java.JavaLanguage.decompileType(JavaLanguage.java:59)
        //     at com.strobel.decompiler.DecompilerDriver.decompileType(DecompilerDriver.java:330)
        //     at com.strobel.decompiler.DecompilerDriver.decompileJar(DecompilerDriver.java:251)
        //     at com.strobel.decompiler.DecompilerDriver.main(DecompilerDriver.java:126)
        // 
        throw new IllegalStateException("An error occurred while decompiling this method.");
    }
}
